sherbystats/__init__.py
sherbystats/anova.py
sherbystats/binaire.py
sherbystats/binaire3D.py
sherbystats/colorspectra.py
sherbystats/doe.py
sherbystats/dtw.py
sherbystats/dtw_multi.py
sherbystats/lags.py
sherbystats/lda.py
sherbystats/mlr.py
sherbystats/normplot.py
sherbystats/pca.py
sherbystats/pca_trou.py
sherbystats/pcr.py
sherbystats/pls.py
sherbystats/ternaire.py
sherbystats/vif.py
sherbystats/vip.py
sherbystats/xlsread.py
sherbystats-0.0.32.dist-info/METADATA
sherbystats-0.0.32.dist-info/WHEEL
sherbystats-0.0.32.dist-info/top_level.txt
sherbystats-0.0.32.dist-info/RECORD
