Metadata-Version: 2.1
Name: sherbystats
Version: 0.0.32
Summary: Ryan @ UdeS
Home-page: https://www.usherbrooke.ca/gchimiquebiotech/departement/professeurs/ryan-gosselin/
Author: Ryan Gosselin
Author-email: ryan.gosselin@usherbrooke.ca
Classifier: Programming Language :: Python :: 3
Classifier: License :: OSI Approved :: MIT License
Classifier: Operating System :: OS Independent
